devtools_rot13/__init__.py
devtools_rot13-1.0.1.dist-info/METADATA
devtools_rot13-1.0.1.dist-info/WHEEL
devtools_rot13-1.0.1.dist-info/top_level.txt
devtools_rot13-1.0.1.dist-info/RECORD
