Metadata-Version: 2.1
Name: devtools-rot13
Version: 1.0.1
Summary: ROT13 encoder/decoder
Home-page: https://devtools.at/tools/rot13
Author: DevTools.at
Author-email: hello@devtools.at
Project-URL: Homepage, https://devtools.at/tools/rot13
Project-URL: Repository, https://github.com/devtools-at/rot13
Classifier: Development Status :: 4 - Beta
Classifier: Intended Audience :: Developers
Classifier: License :: OSI Approved :: MIT License
Classifier: Programming Language :: Python :: 3
Requires-Python: >=3.8
